neo4j_extension/__init__.py
neo4j_extension/py.typed
neo4j_extension/typing.py
neo4j_extension/utils.py
neo4j_extension/bolt/__init__.py
neo4j_extension/bolt/connection.py
neo4j_extension/graph/__init__.py
neo4j_extension/graph/pydantic_action.py
neo4j_extension/graph/pydantic_model.py
neo4j_extension/graph/structure.py
neo4j_extension/types/__init__.py
neo4j_extension/types/_abc.py
neo4j_extension/types/_utils.py
neo4j_extension/types/primitive.py
neo4j_extension/types/spatial.py
neo4j_extension/types/temporal.py
neo4j_extension-0.1.14.dist-info/METADATA
neo4j_extension-0.1.14.dist-info/WHEEL
neo4j_extension-0.1.14.dist-info/top_level.txt
neo4j_extension-0.1.14.dist-info/RECORD
