Metadata-Version: 2.2
Name: neo4j-extension
Version: 0.1.14
Summary: Define types for Neo4j
Requires-Python: >=3.12
Requires-Dist: neo4j>=5.27.0
Requires-Dist: neo4j-rust-ext>=5.27.0.0
Requires-Dist: pydantic>=2.10.6
